imgkernel/__init__.py
imgkernel/imgconv.py
imgkernel/kernels.py
imgkernel-0.0.1.dist-info/LICENSE
imgkernel-0.0.1.dist-info/METADATA
imgkernel-0.0.1.dist-info/WHEEL
imgkernel-0.0.1.dist-info/top_level.txt
imgkernel-0.0.1.dist-info/RECORD
