Metadata-Version: 2.1
Name: imgkernel
Version: 0.0.1
Summary: Image kernel.
Home-page: https://github.com/kenblikylee/imgkernel
Author: ken
Author-email: kenbliky@gmail.com
License: UNKNOWN
Platform: UNKNOWN
Classifier: Programming Language :: Python :: 3
Classifier: License :: OSI Approved :: MIT License
Classifier: Operating System :: OS Independent
Requires-Python: >=3.6
